{ "compressionlevel":0,
 "height":14,
 "infinite":false,
 "layers":[
        {
         "data":[1, 1, 1, 1, 1, 1, 1, 1, 1, 1, 1, 1, 1, 1, 1, 1, 1, 6, 7, 7, 7, 7, 7, 7, 7, 7, 7, 7, 7, 7, 10, 1, 1, 11, 12, 13, 13, 13, 13, 13, 13, 13, 13, 13, 13, 14, 15, 1, 1, 11, 17, 18, 18, 18, 18, 18, 18, 18, 18, 18, 18, 17, 15, 1, 1, 11, 17, 18, 18, 18, 18, 18, 18, 18, 18, 18, 18, 17, 15, 1, 1, 11, 17, 18, 18, 18, 18, 18, 18, 18, 18, 18, 18, 17, 15, 1, 1, 11, 17, 18, 18, 18, 18, 18, 18, 18, 18, 18, 18, 17, 15, 1, 1, 11, 17, 18, 18, 18, 18, 18, 18, 18, 18, 18, 18, 17, 15, 1, 1, 11, 17, 18, 18, 18, 18, 18, 18, 18, 18, 18, 18, 17, 15, 1, 1, 11, 17, 18, 18, 18, 18, 18, 18, 18, 18, 18, 18, 17, 15, 1, 1, 11, 17, 18, 18, 18, 18, 18, 18, 18, 18, 18, 18, 17, 15, 1, 1, 11, 22, 13, 13, 13, 13, 13, 13, 13, 13, 13, 13, 24, 15, 1, 1, 26, 27, 27, 27, 27, 27, 27, 27, 27, 27, 27, 27, 27, 30, 1, 1, 1, 1, 1, 1, 1, 1, 1, 1, 1, 1, 1, 1, 1, 1, 1],
         "height":14,
         "id":1,
         "name":"Board",
         "offsetx":-38,
         "offsety":-38,
         "opacity":1,
         "type":"tilelayer",
         "visible":true,
         "width":16,
         "x":0,
         "y":0
        }, 
        {
         "data":[0, 0, 0, 0, 0, 0, 0, 0, 0, 0, 0, 0, 0, 0, 0, 0, 0, 0, 0, 0, 0, 0, 0, 0, 0, 0, 0, 0, 0, 0, 0, 0, 0, 0, 0, 0, 0, 0, 0, 0, 0, 0, 0, 0, 0, 0, 0, 0, 0, 0, 0, 90, 90, 90, 90, 90, 90, 90, 90, 90, 0, 0, 0, 0, 0, 0, 0, 90, 90, 90, 90, 90, 90, 90, 90, 90, 0, 0, 0, 0, 0, 0, 0, 90, 90, 90, 90, 90, 90, 90, 90, 90, 0, 0, 0, 0, 0, 0, 90, 90, 90, 90, 90, 90, 90, 90, 90, 90, 90, 0, 0, 0, 0, 0, 0, 90, 90, 90, 90, 90, 90, 90, 90, 90, 0, 0, 0, 0, 0, 0, 0, 90, 90, 90, 90, 90, 90, 90, 90, 90, 0, 0, 0, 0, 0, 0, 0, 90, 90, 90, 90, 90, 90, 90, 90, 90, 0, 0, 0, 0, 0, 0, 0, 0, 0, 0, 0, 0, 0, 0, 0, 0, 0, 0, 0, 0, 0, 0, 0, 0, 0, 0, 0, 0, 0, 0, 0, 0, 0, 0, 0, 0, 0, 0, 0, 0, 0, 0, 0, 0, 0, 0, 0, 0, 0, 0, 0, 0, 0, 0, 0, 0, 0, 0, 0, 0, 0, 0, 0, 0, 0, 0, 0, 0],
         "height":14,
         "id":2,
         "name":"Tiles",
         "opacity":1,
         "type":"tilelayer",
         "visible":true,
         "width":16,
         "x":0,
         "y":0
        }, 
        {
         "data":[0, 0, 0, 0, 0, 0, 0, 0, 0, 0, 0, 0, 0, 0, 0, 0, 0, 0, 0, 0, 0, 0, 0, 0, 0, 0, 0, 0, 0, 0, 0, 0, 0, 0, 0, 0, 0, 0, 0, 0, 0, 0, 0, 0, 0, 0, 0, 0, 0, 0, 0, 53, 53, 0, 53, 53, 53, 0, 0, 53, 0, 0, 0, 0, 0, 0, 0, 71, 70, 0, 0, 0, 0, 0, 0, 55, 0, 0, 0, 0, 0, 0, 0, 0, 0, 0, 0, 0, 0, 0, 0, 0, 0, 0, 0, 0, 0, 0, 0, 31, 0, 0, 0, 0, 0, 0, 0, 0, 0, 0, 0, 0, 0, 0, 0, 0, 0, 0, 0, 0, 0, 0, 0, 0, 0, 0, 0, 0, 0, 0, 0, 62, 0, 0, 0, 0, 0, 0, 71, 71, 0, 0, 0, 0, 0, 0, 0, 53, 0, 0, 0, 54, 72, 0, 53, 53, 0, 0, 0, 0, 0, 0, 0, 0, 0, 0, 0, 0, 0, 0, 0, 0, 0, 0, 0, 0, 0, 0, 0, 0, 0, 0, 0, 0, 0, 0, 0, 0, 0, 0, 0, 0, 0, 0, 0, 0, 0, 0, 0, 0, 0, 0, 0, 0, 0, 0, 0, 0, 0, 0, 0, 0, 0, 0, 0, 0, 0, 0, 0, 0, 0, 0, 0, 0],
         "height":14,
         "id":3,
         "name":"Assets",
         "opacity":1,
         "type":"tilelayer",
         "visible":true,
         "width":16,
         "x":0,
         "y":0
        }, 
        {
         "data":[0, 0, 0, 0, 0, 0, 0, 0, 0, 0, 0, 0, 0, 0, 0, 0, 0, 0, 0, 0, 0, 0, 0, 0, 0, 0, 0, 0, 0, 0, 0, 0, 0, 0, 0, 0, 195, 165, 0, 193, 194, 0, 163, 164, 0, 0, 0, 0, 0, 0, 0, 0, 0, 0, 0, 0, 0, 0, 0, 0, 0, 0, 0, 0, 0, 0, 179, 0, 0, 0, 0, 0, 0, 0, 0, 0, 0, 180, 0, 0, 0, 0, 0, 0, 0, 0, 0, 0, 0, 0, 0, 0, 0, 0, 0, 0, 0, 0, 187, 0, 0, 0, 0, 0, 0, 0, 0, 0, 0, 188, 0, 0, 0, 0, 201, 0, 0, 0, 0, 0, 0, 0, 0, 0, 0, 202, 0, 0, 0, 0, 0, 0, 0, 0, 0, 0, 0, 0, 0, 0, 0, 0, 0, 0, 0, 0, 191, 0, 0, 0, 0, 0, 0, 0, 0, 0, 0, 192, 0, 0, 0, 0, 205, 0, 0, 0, 0, 0, 0, 0, 0, 0, 0, 206, 0, 0, 0, 0, 0, 0, 166, 209, 0, 207, 208, 0, 177, 178, 0, 0, 0, 0, 0, 0, 0, 0, 0, 0, 0, 0, 0, 0, 0, 0, 0, 0, 0, 0, 0, 0, 0, 0, 0, 0, 0, 0, 0, 0, 0, 0, 0, 0, 0, 0],
         "height":14,
         "id":7,
         "name":"Decorations",
         "offsetx":-38,
         "offsety":-38,
         "opacity":1,
         "type":"tilelayer",
         "visible":true,
         "width":16,
         "x":0,
         "y":0
        }, 
        {
         "draworder":"topdown",
         "id":8,
         "name":"Random Pickup",
         "objects":[
                {
                 "height":525,
                 "id":33,
                 "name":"",
                 "rotation":0,
                 "type":"",
                 "visible":true,
                 "width":525,
                 "x":375,
                 "y":225
                }, 
                {
                 "gid":44,
                 "height":75,
                 "id":34,
                 "name":"",
                 "rotation":0,
                 "type":"",
                 "visible":true,
                 "width":75,
                 "x":375,
                 "y":750
                }, 
                {
                 "gid":44,
                 "height":75,
                 "id":35,
                 "name":"",
                 "rotation":0,
                 "type":"",
                 "visible":true,
                 "width":75,
                 "x":450,
                 "y":750
                }],
         "opacity":1,
         "type":"objectgroup",
         "visible":true,
         "x":0,
         "y":0
        }, 
        {
         "color":"#0a16fa",
         "draworder":"topdown",
         "id":4,
         "name":"Random Key",
         "objects":[
                {
                 "height":300,
                 "id":13,
                 "name":"",
                 "rotation":0,
                 "type":"",
                 "visible":true,
                 "width":450,
                 "x":375,
                 "y":225
                }, 
                {
                 "gid":42,
                 "height":75,
                 "id":20,
                 "name":"",
                 "rotation":0,
                 "type":"",
                 "visible":true,
                 "width":75,
                 "x":450,
                 "y":375
                }],
         "opacity":0.67,
         "type":"objectgroup",
         "visible":true,
         "x":0,
         "y":0
        }, 
        {
         "color":"#e51418",
         "draworder":"topdown",
         "id":5,
         "name":"Random Enemies",
         "objects":[
                {
                 "height":525,
                 "id":1,
                 "name":"",
                 "rotation":0,
                 "type":"",
                 "visible":true,
                 "width":75,
                 "x":375,
                 "y":225
                }, 
                {
                 "height":375,
                 "id":6,
                 "name":"",
                 "rotation":0,
                 "type":"",
                 "visible":true,
                 "width":150,
                 "x":675,
                 "y":225
                }, 
                {
                 "height":150,
                 "id":7,
                 "name":"",
                 "rotation":0,
                 "type":"",
                 "visible":true,
                 "width":225,
                 "x":450,
                 "y":525
                }, 
                {
                 "gid":33,
                 "height":75,
                 "id":23,
                 "name":"",
                 "rotation":0,
                 "type":"",
                 "visible":true,
                 "width":75,
                 "x":675,
                 "y":450
                }, 
                {
                 "gid":33,
                 "height":75,
                 "id":24,
                 "name":"",
                 "rotation":0,
                 "type":"",
                 "visible":true,
                 "width":75,
                 "x":675,
                 "y":525
                }, 
                {
                 "gid":33,
                 "height":75,
                 "id":25,
                 "name":"",
                 "rotation":0,
                 "type":"",
                 "visible":true,
                 "width":75,
                 "x":525,
                 "y":600
                }, 
                {
                 "gid":33,
                 "height":75,
                 "id":26,
                 "name":"",
                 "rotation":0,
                 "type":"",
                 "visible":true,
                 "width":75,
                 "x":525,
                 "y":675
                }, 
                {
                 "gid":33,
                 "height":75,
                 "id":27,
                 "name":"",
                 "rotation":0,
                 "type":"",
                 "visible":true,
                 "width":75,
                 "x":375,
                 "y":450
                }, 
                {
                 "gid":33,
                 "height":75,
                 "id":28,
                 "name":"",
                 "rotation":0,
                 "type":"",
                 "visible":true,
                 "width":75,
                 "x":375,
                 "y":525
                }],
         "opacity":0.64,
         "type":"objectgroup",
         "visible":true,
         "x":0,
         "y":0
        }, 
        {
         "color":"#15e606",
         "draworder":"topdown",
         "id":6,
         "name":"Scramble Enemies",
         "objects":[
                {
                 "height":75,
                 "id":31,
                 "name":"",
                 "rotation":0,
                 "type":"",
                 "visible":true,
                 "width":75,
                 "x":525,
                 "y":375
                }, 
                {
                 "gid":34,
                 "height":75,
                 "id":32,
                 "name":"",
                 "rotation":0,
                 "type":"",
                 "visible":true,
                 "width":75,
                 "x":525,
                 "y":450
                }],
         "opacity":0.66,
         "type":"objectgroup",
         "visible":true,
         "x":0,
         "y":0
        }],
 "nextlayerid":9,
 "nextobjectid":36,
 "orientation":"orthogonal",
 "renderorder":"right-down",
 "tiledversion":"1.8.2",
 "tileheight":75,
 "tilesets":[
        {
         "columns":5,
         "firstgid":1,
         "image":"tilesets\/lab.png",
         "imageheight":450,
         "imagewidth":375,
         "margin":0,
         "name":"lab",
         "spacing":0,
         "tilecount":30,
         "tileheight":75,
         "tilewidth":75
        }, 
        {
         "firstgid":31,
         "source":"assets.json"
        }, 
        {
         "firstgid":103,
         "source":"decorations.json"
        }],
 "tilewidth":75,
 "type":"map",
 "version":"1.8",
 "width":16
}